Workbook

Sheet Read me
B1: Capital IQ Pro — Revenue-forecasting signal puller
B3: What this is
B4: A template of live =CIQ(...) formulas for the 100-company universe. It pulls the signals most likely to improve the next-quarter revenue-growth model — above all CONSENSUS ESTIMATES, which the SEC/price data cannot provide.
B6: How to use it
B7: 1. Open in Excel with the Capital IQ Office plug-in installed and logged in (Capital IQ ribbon).
B8: 2. Press Refresh (Capital IQ ribbon) or Ctrl+Alt+F9 to pull. First refresh can take a minute.
B9: 3. Each data column has its MNEMONIC in row 2 and its PERIOD in row 3 (both blue = editable). If a column errors, fix that one mnemonic/period cell and the whole column updates.
B10: 4. Add tickers on 'Universe'; the data sheets read from it, so extend formulas down to match.
B12: IMPORTANT — verify mnemonics
B13: Exact CIQ mnemonic spellings vary slightly by account/version (e.g. IQ_TOTAL_REV_MEDIAN_EST vs IQ_TOTAL_REV_EST_MEDIAN). Yellow header cells are best-guess strings to VERIFY once in the CIQ ribbon → Formula Builder, then they are locked in for every row. Nothing here can resolve without the plug-in.
B15: Period syntax (put in row 3 cells)
B16: IQ_FQ = latest reported fiscal quarter · IQ_FQ-1, IQ_FQ-2 … = prior quarters · IQ_FQ+1, IQ_FQ+2 … = forward (estimate) quarters · IQ_FY / IQ_FY+1 = fiscal year / next · IQ_LTM = last twelve months · IQ_CY / IQ_CQ = calendar year / quarter.
... B26: CIQ resolves plain tickers (AAPL) for US names; for ambiguity use exchange prefix (NASDAQ:AAPL, NYSE:JPM) or ticker:country (AAPL:US). BRK.B may need 'BRK.B:US'. Adjust the 'CIQ ID' column on Universe if a row fails.

Sheet Universe
A1: Ticker | B1: Sector | C1: CIQ ID
A2: CHTR | B2: Communication Services | C2: =A2
A3: CMCSA | B3: Communication Services | C3: =A3
A4: DIS | B4: Communication Services | C4: =A4
A5: EA | B5: Communication Services | C5: =A5
A6: NFLX | B6: Communication Services | C6: =A6
A7: T | B7: Communication Services | C7: =A7
A8: TMUS | B8: Communication Services | C8: =A8
A9: TTWO | B9: Communication Services | C9: =A9
A10: VZ | B10: Communication Services | C10: =A10
A11: WBD | B11: Communication Services | C11: =A11
A12: AMZN | B12: Consumer Discretionary | C12: =A12
A13: BKNG | B13: Consumer Discretionary | C13: =A13
... A101: ORCL | B101: Technology | C101: =A101

Sheet Estimates
A1: Ticker | B1: Rev est mean +1 | C1: Rev est # +1 | D1: Rev est high +1 | E1: Rev est low +1 | F1: Rev est stdev +1 | G1: Rev est mean +2 | H1: Rev est # +2 | I1: Rev est high +2 | J1: Rev est low +2 | K1: Rev est stdev +2 | L1: Rev est mean +3 | M1: Rev est # +3 | N1: Rev est high +3 | O1: Rev est low +3 | P1: Rev est stdev +3 | Q1: Rev est mean +4 | R1: Rev est # +4 | S1: Rev est high +4 | T1: Rev est low +4 | U1: Rev est stdev +4 | V1: EPS est mean +1 | W1: EPS est # +1 | X1: EBITDA est +1 | Y1: Rev est FY+1 | Z1: Rev est FY+2
A2: mnemonic → | B2: IQ_TOTAL_REV_EST | C2: IQ_TOTAL_REV_NUM_EST | D2: IQ_TOTAL_REV_HIGH_EST | E2: IQ_TOTAL_REV_LOW_EST | F2: IQ_TOTAL_REV_STDDEV_EST | G2: IQ_TOTAL_REV_EST | H2: IQ_TOTAL_REV_NUM_EST | I2: IQ_TOTAL_REV_HIGH_EST | J2: IQ_TOTAL_REV_LOW_EST | K2: IQ_TOTAL_REV_STDDEV_EST | L2: IQ_TOTAL_REV_EST | M2: IQ_TOTAL_REV_NUM_EST | N2: IQ_TOTAL_REV_HIGH_EST | O2: IQ_TOTAL_REV_LOW_EST | P2: IQ_TOTAL_REV_STDDEV_EST | Q2: IQ_TOTAL_REV_EST | R2: IQ_TOTAL_REV_NUM_EST | S2: IQ_TOTAL_REV_HIGH_EST | T2: IQ_TOTAL_REV_LOW_EST | U2: IQ_TOTAL_REV_STDDEV_EST | V2: IQ_EPS_NORM_EST | W2: IQ_EPS_NORM_NUM_EST | X2: IQ_EBITDA_EST | Y2: IQ_TOTAL_REV_EST | Z2: IQ_TOTAL_REV_EST
A3: period → | B3: IQ_FQ+1 | C3: IQ_FQ+1 | D3: IQ_FQ+1 | E3: IQ_FQ+1 | F3: IQ_FQ+1 | G3: IQ_FQ+2 | H3: IQ_FQ+2 | I3: IQ_FQ+2 | J3: IQ_FQ+2 | K3: IQ_FQ+2 | L3: IQ_FQ+3 | M3: IQ_FQ+3 | N3: IQ_FQ+3 | O3: IQ_FQ+3 | P3: IQ_FQ+3 | Q3: IQ_FQ+4 | R3: IQ_FQ+4 | S3: IQ_FQ+4 | T3: IQ_FQ+4 | U3: IQ_FQ+4 | V3: IQ_FQ+1 | W3: IQ_FQ+1 | X3: IQ_FQ+1 | Y3: IQ_FY+1 | Z3: IQ_FY+2
A4: =Universe!C2 | B4: =CIQ($A4,B$2,B$3) | C4: =CIQ($A4,C$2,C$3) | D4: =CIQ($A4,D$2,D$3) | E4: =CIQ($A4,E$2,E$3) | F4: =CIQ($A4,F$2,F$3) | G4: =CIQ($A4,G$2,G$3) | H4: =CIQ($A4,H$2,H$3) | I4: =CIQ($A4,I$2,I$3) | ... Z4: =CIQ($A4,Z$2,Z$3)
A5: =Universe!C3 | B5: =CIQ($A5,B$2,B$3) | C5: =CIQ($A5,C$2,C$3) | D5: =CIQ($A5,D$2,D$3) | E5: =CIQ($A5,E$2,E$3) | F5: =CIQ($A5,F$2,F$3) | G5: =CIQ($A5,G$2,G$3) | H5: =CIQ($A5,H$2,H$3) | I5: =CIQ($A5,I$2,I$3) | ... Z5: =CIQ($A5,Z$2,Z$3)
A6: =Universe!C4 | B6: =CIQ($A6,B$2,B$3) | C6: =CIQ($A6,C$2,C$3) | D6: =CIQ($A6,D$2,D$3) | E6: =CIQ($A6,E$2,E$3) | F6: =CIQ($A6,F$2,F$3) | G6: =CIQ($A6,G$2,G$3) | H6: =CIQ($A6,H$2,H$3) | I6: =CIQ($A6,I$2,I$3) | ... Z6: =CIQ($A6,Z$2,Z$3)
A7: =Universe!C5 | B7: =CIQ($A7,B$2,B$3) | C7: =CIQ($A7,C$2,C$3) | D7: =CIQ($A7,D$2,D$3) | E7: =CIQ($A7,E$2,E$3) | F7: =CIQ($A7,F$2,F$3) | G7: =CIQ($A7,G$2,G$3) | H7: =CIQ($A7,H$2,H$3) | I7: =CIQ($A7,I$2,I$3) | ... Z7: =CIQ($A7,Z$2,Z$3)
A8: =Universe!C6 | B8: =CIQ($A8,B$2,B$3) | C8: =CIQ($A8,C$2,C$3) | D8: =CIQ($A8,D$2,D$3) | E8: =CIQ($A8,E$2,E$3) | F8: =CIQ($A8,F$2,F$3) | G8: =CIQ($A8,G$2,G$3) | H8: =CIQ($A8,H$2,H$3) | I8: =CIQ($A8,I$2,I$3) | ... Z8: =CIQ($A8,Z$2,Z$3)
A9: =Universe!C7 | B9: =CIQ($A9,B$2,B$3) | C9: =CIQ($A9,C$2,C$3) | D9: =CIQ($A9,D$2,D$3) | E9: =CIQ($A9,E$2,E$3) | F9: =CIQ($A9,F$2,F$3) | G9: =CIQ($A9,G$2,G$3) | H9: =CIQ($A9,H$2,H$3) | I9: =CIQ($A9,I$2,I$3) | ... Z9: =CIQ($A9,Z$2,Z$3)
A10: =Universe!C8 | B10: =CIQ($A10,B$2,B$3) | C10: =CIQ($A10,C$2,C$3) | D10: =CIQ($A10,D$2,D$3) | E10: =CIQ($A10,E$2,E$3) | F10: =CIQ($A10,F$2,F$3) | G10: =CIQ($A10,G$2,G$3) | H10: =CIQ($A10,H$2,H$3) | I10: =CIQ($A10,I$2,I$3) | ... Z10: =CIQ($A10,Z$2,Z$3)
A11: =Universe!C9 | B11: =CIQ($A11,B$2,B$3) | C11: =CIQ($A11,C$2,C$3) | D11: =CIQ($A11,D$2,D$3) | E11: =CIQ($A11,E$2,E$3) | F11: =CIQ($A11,F$2,F$3) | G11: =CIQ($A11,G$2,G$3) | H11: =CIQ($A11,H$2,H$3) | I11: =CIQ($A11,I$2,I$3) | ... Z11: =CIQ($A11,Z$2,Z$3)
A12: =Universe!C10 | B12: =CIQ($A12,B$2,B$3) | C12: =CIQ($A12,C$2,C$3) | D12: =CIQ($A12,D$2,D$3) | E12: =CIQ($A12,E$2,E$3) | F12: =CIQ($A12,F$2,F$3) | G12: =CIQ($A12,G$2,G$3) | H12: =CIQ($A12,H$2,H$3) | I12: =CIQ($A12,I$2,I$3) | ... Z12: =CIQ($A12,Z$2,Z$3)
A13: =Universe!C11 | B13: =CIQ($A13,B$2,B$3) | C13: =CIQ($A13,C$2,C$3) | D13: =CIQ($A13,D$2,D$3) | E13: =CIQ($A13,E$2,E$3) | F13: =CIQ($A13,F$2,F$3) | G13: =CIQ($A13,G$2,G$3) | H13: =CIQ($A13,H$2,H$3) | I13: =CIQ($A13,I$2,I$3) | ... Z13: =CIQ($A13,Z$2,Z$3)
A14: =Universe!C12 | B14: =CIQ($A14,B$2,B$3) | C14: =CIQ($A14,C$2,C$3) | D14: =CIQ($A14,D$2,D$3) | E14: =CIQ($A14,E$2,E$3) | F14: =CIQ($A14,F$2,F$3) | G14: =CIQ($A14,G$2,G$3) | H14: =CIQ($A14,H$2,H$3) | I14: =CIQ($A14,I$2,I$3) | ... Z14: =CIQ($A14,Z$2,Z$3)
A15: =Universe!C13 | B15: =CIQ($A15,B$2,B$3) | C15: =CIQ($A15,C$2,C$3) | D15: =CIQ($A15,D$2,D$3) | E15: =CIQ($A15,E$2,E$3) | F15: =CIQ($A15,F$2,F$3) | G15: =CIQ($A15,G$2,G$3) | H15: =CIQ($A15,H$2,H$3) | I15: =CIQ($A15,I$2,I$3) | ... Z15: =CIQ($A15,Z$2,Z$3)
... A103: =Universe!C101 | B103: =CIQ($A103,B$2,B$3) | C103: =CIQ($A103,C$2,C$3) | D103: =CIQ($A103,D$2,D$3) | E103: =CIQ($A103,E$2,E$3) | F103: =CIQ($A103,F$2,F$3) | G103: =CIQ($A103,G$2,G$3) | H103: =CIQ($A103,H$2,H$3) | I103: =CIQ($A103,I$2,I$3) | ... Z103: =CIQ($A103,Z$2,Z$3)

Sheet Actuals & Surprise
A1: Ticker | B1: Revenue Q | C1: Revenue Q-1 | D1: Revenue Q-2 | E1: Revenue Q-3 | F1: Revenue Q-4 | G1: Rev surprise % Q | H1: Rev surprise % Q-1 | I1: EPS actual Q | J1: EPS surprise % Q | K1: Period end date Q | L1: Filing date Q | M1: Filing date Q-1
A2: mnemonic → | B2: IQ_TOTAL_REV | C2: IQ_TOTAL_REV | D2: IQ_TOTAL_REV | E2: IQ_TOTAL_REV | F2: IQ_TOTAL_REV | G2: IQ_REV_SURPRISE_PERCENT | H2: IQ_REV_SURPRISE_PERCENT | I2: IQ_EPS_NORM | J2: IQ_EPS_SURPRISE_PERCENT | K2: IQ_PERIOD_DATE | L2: IQ_FILING_DATE | M2: IQ_FILING_DATE
A3: period → | B3: IQ_FQ | C3: IQ_FQ-1 | D3: IQ_FQ-2 | E3: IQ_FQ-3 | F3: IQ_FQ-4 | G3: IQ_FQ | H3: IQ_FQ-1 | I3: IQ_FQ | J3: IQ_FQ | K3: IQ_FQ | L3: IQ_FQ | M3: IQ_FQ-1
A4: =Universe!C2 | B4: =CIQ($A4,B$2,B$3) | C4: =CIQ($A4,C$2,C$3) | D4: =CIQ($A4,D$2,D$3) | E4: =CIQ($A4,E$2,E$3) | F4: =CIQ($A4,F$2,F$3) | G4: =CIQ($A4,G$2,G$3) | H4: =CIQ($A4,H$2,H$3) | I4: =CIQ($A4,I$2,I$3) | ... M4: =CIQ($A4,M$2,M$3)
A5: =Universe!C3 | B5: =CIQ($A5,B$2,B$3) | C5: =CIQ($A5,C$2,C$3) | D5: =CIQ($A5,D$2,D$3) | E5: =CIQ($A5,E$2,E$3) | F5: =CIQ($A5,F$2,F$3) | G5: =CIQ($A5,G$2,G$3) | H5: =CIQ($A5,H$2,H$3) | I5: =CIQ($A5,I$2,I$3) | ... M5: =CIQ($A5,M$2,M$3)
A6: =Universe!C4 | B6: =CIQ($A6,B$2,B$3) | C6: =CIQ($A6,C$2,C$3) | D6: =CIQ($A6,D$2,D$3) | E6: =CIQ($A6,E$2,E$3) | F6: =CIQ($A6,F$2,F$3) | G6: =CIQ($A6,G$2,G$3) | H6: =CIQ($A6,H$2,H$3) | I6: =CIQ($A6,I$2,I$3) | ... M6: =CIQ($A6,M$2,M$3)
A7: =Universe!C5 | B7: =CIQ($A7,B$2,B$3) | C7: =CIQ($A7,C$2,C$3) | D7: =CIQ($A7,D$2,D$3) | E7: =CIQ($A7,E$2,E$3) | F7: =CIQ($A7,F$2,F$3) | G7: =CIQ($A7,G$2,G$3) | H7: =CIQ($A7,H$2,H$3) | I7: =CIQ($A7,I$2,I$3) | ... M7: =CIQ($A7,M$2,M$3)
A8: =Universe!C6 | B8: =CIQ($A8,B$2,B$3) | C8: =CIQ($A8,C$2,C$3) | D8: =CIQ($A8,D$2,D$3) | E8: =CIQ($A8,E$2,E$3) | F8: =CIQ($A8,F$2,F$3) | G8: =CIQ($A8,G$2,G$3) | H8: =CIQ($A8,H$2,H$3) | I8: =CIQ($A8,I$2,I$3) | ... M8: =CIQ($A8,M$2,M$3)
A9: =Universe!C7 | B9: =CIQ($A9,B$2,B$3) | C9: =CIQ($A9,C$2,C$3) | D9: =CIQ($A9,D$2,D$3) | E9: =CIQ($A9,E$2,E$3) | F9: =CIQ($A9,F$2,F$3) | G9: =CIQ($A9,G$2,G$3) | H9: =CIQ($A9,H$2,H$3) | I9: =CIQ($A9,I$2,I$3) | ... M9: =CIQ($A9,M$2,M$3)
A10: =Universe!C8 | B10: =CIQ($A10,B$2,B$3) | C10: =CIQ($A10,C$2,C$3) | D10: =CIQ($A10,D$2,D$3) | E10: =CIQ($A10,E$2,E$3) | F10: =CIQ($A10,F$2,F$3) | G10: =CIQ($A10,G$2,G$3) | H10: =CIQ($A10,H$2,H$3) | I10: =CIQ($A10,I$2,I$3) | ... M10: =CIQ($A10,M$2,M$3)
A11: =Universe!C9 | B11: =CIQ($A11,B$2,B$3) | C11: =CIQ($A11,C$2,C$3) | D11: =CIQ($A11,D$2,D$3) | E11: =CIQ($A11,E$2,E$3) | F11: =CIQ($A11,F$2,F$3) | G11: =CIQ($A11,G$2,G$3) | H11: =CIQ($A11,H$2,H$3) | I11: =CIQ($A11,I$2,I$3) | ... M11: =CIQ($A11,M$2,M$3)
A12: =Universe!C10 | B12: =CIQ($A12,B$2,B$3) | C12: =CIQ($A12,C$2,C$3) | D12: =CIQ($A12,D$2,D$3) | E12: =CIQ($A12,E$2,E$3) | F12: =CIQ($A12,F$2,F$3) | G12: =CIQ($A12,G$2,G$3) | H12: =CIQ($A12,H$2,H$3) | I12: =CIQ($A12,I$2,I$3) | ... M12: =CIQ($A12,M$2,M$3)
A13: =Universe!C11 | B13: =CIQ($A13,B$2,B$3) | C13: =CIQ($A13,C$2,C$3) | D13: =CIQ($A13,D$2,D$3) | E13: =CIQ($A13,E$2,E$3) | F13: =CIQ($A13,F$2,F$3) | G13: =CIQ($A13,G$2,G$3) | H13: =CIQ($A13,H$2,H$3) | I13: =CIQ($A13,I$2,I$3) | ... M13: =CIQ($A13,M$2,M$3)
A14: =Universe!C12 | B14: =CIQ($A14,B$2,B$3) | C14: =CIQ($A14,C$2,C$3) | D14: =CIQ($A14,D$2,D$3) | E14: =CIQ($A14,E$2,E$3) | F14: =CIQ($A14,F$2,F$3) | G14: =CIQ($A14,G$2,G$3) | H14: =CIQ($A14,H$2,H$3) | I14: =CIQ($A14,I$2,I$3) | ... M14: =CIQ($A14,M$2,M$3)
A15: =Universe!C13 | B15: =CIQ($A15,B$2,B$3) | C15: =CIQ($A15,C$2,C$3) | D15: =CIQ($A15,D$2,D$3) | E15: =CIQ($A15,E$2,E$3) | F15: =CIQ($A15,F$2,F$3) | G15: =CIQ($A15,G$2,G$3) | H15: =CIQ($A15,H$2,H$3) | I15: =CIQ($A15,I$2,I$3) | ... M15: =CIQ($A15,M$2,M$3)
... A103: =Universe!C101 | B103: =CIQ($A103,B$2,B$3) | C103: =CIQ($A103,C$2,C$3) | D103: =CIQ($A103,D$2,D$3) | E103: =CIQ($A103,E$2,E$3) | F103: =CIQ($A103,F$2,F$3) | G103: =CIQ($A103,G$2,G$3) | H103: =CIQ($A103,H$2,H$3) | I103: =CIQ($A103,I$2,I$3) | ... M103: =CIQ($A103,M$2,M$3)

Sheet Guidance
A1: Ticker | B1: Rev guid high FQ+1 | C1: Rev guid low FQ+1 | D1: Rev guid high FY+1 | E1: Rev guid low FY+1 | F1: EPS guid high FY+1 | G1: EPS guid low FY+1
A2: mnemonic → | B2: IQ_REV_GUIDANCE_HIGH | C2: IQ_REV_GUIDANCE_LOW | D2: IQ_REV_GUIDANCE_HIGH | E2: IQ_REV_GUIDANCE_LOW | F2: IQ_EPS_GUIDANCE_HIGH | G2: IQ_EPS_GUIDANCE_LOW
A3: period → | B3: IQ_FQ+1 | C3: IQ_FQ+1 | D3: IQ_FY+1 | E3: IQ_FY+1 | F3: IQ_FY+1 | G3: IQ_FY+1
A4: =Universe!C2 | B4: =CIQ($A4,B$2,B$3) | C4: =CIQ($A4,C$2,C$3) | D4: =CIQ($A4,D$2,D$3) | E4: =CIQ($A4,E$2,E$3) | F4: =CIQ($A4,F$2,F$3) | G4: =CIQ($A4,G$2,G$3)
A5: =Universe!C3 | B5: =CIQ($A5,B$2,B$3) | C5: =CIQ($A5,C$2,C$3) | D5: =CIQ($A5,D$2,D$3) | E5: =CIQ($A5,E$2,E$3) | F5: =CIQ($A5,F$2,F$3) | G5: =CIQ($A5,G$2,G$3)
A6: =Universe!C4 | B6: =CIQ($A6,B$2,B$3) | C6: =CIQ($A6,C$2,C$3) | D6: =CIQ($A6,D$2,D$3) | E6: =CIQ($A6,E$2,E$3) | F6: =CIQ($A6,F$2,F$3) | G6: =CIQ($A6,G$2,G$3)
A7: =Universe!C5 | B7: =CIQ($A7,B$2,B$3) | C7: =CIQ($A7,C$2,C$3) | D7: =CIQ($A7,D$2,D$3) | E7: =CIQ($A7,E$2,E$3) | F7: =CIQ($A7,F$2,F$3) | G7: =CIQ($A7,G$2,G$3)
A8: =Universe!C6 | B8: =CIQ($A8,B$2,B$3) | C8: =CIQ($A8,C$2,C$3) | D8: =CIQ($A8,D$2,D$3) | E8: =CIQ($A8,E$2,E$3) | F8: =CIQ($A8,F$2,F$3) | G8: =CIQ($A8,G$2,G$3)
A9: =Universe!C7 | B9: =CIQ($A9,B$2,B$3) | C9: =CIQ($A9,C$2,C$3) | D9: =CIQ($A9,D$2,D$3) | E9: =CIQ($A9,E$2,E$3) | F9: =CIQ($A9,F$2,F$3) | G9: =CIQ($A9,G$2,G$3)
A10: =Universe!C8 | B10: =CIQ($A10,B$2,B$3) | C10: =CIQ($A10,C$2,C$3) | D10: =CIQ($A10,D$2,D$3) | E10: =CIQ($A10,E$2,E$3) | F10: =CIQ($A10,F$2,F$3) | G10: =CIQ($A10,G$2,G$3)
A11: =Universe!C9 | B11: =CIQ($A11,B$2,B$3) | C11: =CIQ($A11,C$2,C$3) | D11: =CIQ($A11,D$2,D$3) | E11: =CIQ($A11,E$2,E$3) | F11: =CIQ($A11,F$2,F$3) | G11: =CIQ($A11,G$2,G$3)
A12: =Universe!C10 | B12: =CIQ($A12,B$2,B$3) | C12: =CIQ($A12,C$2,C$3) | D12: =CIQ($A12,D$2,D$3) | E12: =CIQ($A12,E$2,E$3) | F12: =CIQ($A12,F$2,F$3) | G12: =CIQ($A12,G$2,G$3)
A13: =Universe!C11 | B13: =CIQ($A13,B$2,B$3) | C13: =CIQ($A13,C$2,C$3) | D13: =CIQ($A13,D$2,D$3) | E13: =CIQ($A13,E$2,E$3) | F13: =CIQ($A13,F$2,F$3) | G13: =CIQ($A13,G$2,G$3)
A14: =Universe!C12 | B14: =CIQ($A14,B$2,B$3) | C14: =CIQ($A14,C$2,C$3) | D14: =CIQ($A14,D$2,D$3) | E14: =CIQ($A14,E$2,E$3) | F14: =CIQ($A14,F$2,F$3) | G14: =CIQ($A14,G$2,G$3)
A15: =Universe!C13 | B15: =CIQ($A15,B$2,B$3) | C15: =CIQ($A15,C$2,C$3) | D15: =CIQ($A15,D$2,D$3) | E15: =CIQ($A15,E$2,E$3) | F15: =CIQ($A15,F$2,F$3) | G15: =CIQ($A15,G$2,G$3)
... A103: =Universe!C101 | B103: =CIQ($A103,B$2,B$3) | C103: =CIQ($A103,C$2,C$3) | D103: =CIQ($A103,D$2,D$3) | E103: =CIQ($A103,E$2,E$3) | F103: =CIQ($A103,F$2,F$3) | G103: =CIQ($A103,G$2,G$3)

Sheet Pricing & Valuation
A1: Ticker | B1: Close price | C1: Market cap | D1: TEV | E1: P/E (LTM) | F1: EV/EBITDA (LTM) | G1: EV/Revenue (LTM)
A2: mnemonic → | B2: IQ_CLOSEPRICE | C2: IQ_MARKETCAP | D2: IQ_TEV | E2: IQ_PE_EXCL | F2: IQ_TEV_EBITDA | G2: IQ_TEV_TOTAL_REV
A3: period → | B3: IQ_CY | C3: IQ_CY | D3: IQ_CY | E3: IQ_LTM | F3: IQ_LTM | G3: IQ_LTM
A4: =Universe!C2 | B4: =CIQ($A4,B$2,B$3) | C4: =CIQ($A4,C$2,C$3) | D4: =CIQ($A4,D$2,D$3) | E4: =CIQ($A4,E$2,E$3) | F4: =CIQ($A4,F$2,F$3) | G4: =CIQ($A4,G$2,G$3)
A5: =Universe!C3 | B5: =CIQ($A5,B$2,B$3) | C5: =CIQ($A5,C$2,C$3) | D5: =CIQ($A5,D$2,D$3) | E5: =CIQ($A5,E$2,E$3) | F5: =CIQ($A5,F$2,F$3) | G5: =CIQ($A5,G$2,G$3)
A6: =Universe!C4 | B6: =CIQ($A6,B$2,B$3) | C6: =CIQ($A6,C$2,C$3) | D6: =CIQ($A6,D$2,D$3) | E6: =CIQ($A6,E$2,E$3) | F6: =CIQ($A6,F$2,F$3) | G6: =CIQ($A6,G$2,G$3)
A7: =Universe!C5 | B7: =CIQ($A7,B$2,B$3) | C7: =CIQ($A7,C$2,C$3) | D7: =CIQ($A7,D$2,D$3) | E7: =CIQ($A7,E$2,E$3) | F7: =CIQ($A7,F$2,F$3) | G7: =CIQ($A7,G$2,G$3)
A8: =Universe!C6 | B8: =CIQ($A8,B$2,B$3) | C8: =CIQ($A8,C$2,C$3) | D8: =CIQ($A8,D$2,D$3) | E8: =CIQ($A8,E$2,E$3) | F8: =CIQ($A8,F$2,F$3) | G8: =CIQ($A8,G$2,G$3)
A9: =Universe!C7 | B9: =CIQ($A9,B$2,B$3) | C9: =CIQ($A9,C$2,C$3) | D9: =CIQ($A9,D$2,D$3) | E9: =CIQ($A9,E$2,E$3) | F9: =CIQ($A9,F$2,F$3) | G9: =CIQ($A9,G$2,G$3)
A10: =Universe!C8 | B10: =CIQ($A10,B$2,B$3) | C10: =CIQ($A10,C$2,C$3) | D10: =CIQ($A10,D$2,D$3) | E10: =CIQ($A10,E$2,E$3) | F10: =CIQ($A10,F$2,F$3) | G10: =CIQ($A10,G$2,G$3)
A11: =Universe!C9 | B11: =CIQ($A11,B$2,B$3) | C11: =CIQ($A11,C$2,C$3) | D11: =CIQ($A11,D$2,D$3) | E11: =CIQ($A11,E$2,E$3) | F11: =CIQ($A11,F$2,F$3) | G11: =CIQ($A11,G$2,G$3)
A12: =Universe!C10 | B12: =CIQ($A12,B$2,B$3) | C12: =CIQ($A12,C$2,C$3) | D12: =CIQ($A12,D$2,D$3) | E12: =CIQ($A12,E$2,E$3) | F12: =CIQ($A12,F$2,F$3) | G12: =CIQ($A12,G$2,G$3)
A13: =Universe!C11 | B13: =CIQ($A13,B$2,B$3) | C13: =CIQ($A13,C$2,C$3) | D13: =CIQ($A13,D$2,D$3) | E13: =CIQ($A13,E$2,E$3) | F13: =CIQ($A13,F$2,F$3) | G13: =CIQ($A13,G$2,G$3)
A14: =Universe!C12 | B14: =CIQ($A14,B$2,B$3) | C14: =CIQ($A14,C$2,C$3) | D14: =CIQ($A14,D$2,D$3) | E14: =CIQ($A14,E$2,E$3) | F14: =CIQ($A14,F$2,F$3) | G14: =CIQ($A14,G$2,G$3)
A15: =Universe!C13 | B15: =CIQ($A15,B$2,B$3) | C15: =CIQ($A15,C$2,C$3) | D15: =CIQ($A15,D$2,D$3) | E15: =CIQ($A15,E$2,E$3) | F15: =CIQ($A15,F$2,F$3) | G15: =CIQ($A15,G$2,G$3)
... A103: =Universe!C101 | B103: =CIQ($A103,B$2,B$3) | C103: =CIQ($A103,C$2,C$3) | D103: =CIQ($A103,D$2,D$3) | E103: =CIQ($A103,E$2,E$3) | F103: =CIQ($A103,F$2,F$3) | G103: =CIQ($A103,G$2,G$3)
